{
    "actions": {
        "save": "حفظ",
        "cancel": "إلغاء",
        "confirm": "تأكيد",
        "delete": "حذف",
        "edit": "تعديل",
        "add": "إضافة",
        "close": "إغلاق",
        "back": "رجوع",
        "next": "التالي",
        "logout": "تسجيل الخروج"
    },
    "status": {
        "loading": "جارٍ التحميل...",
        "success": "تم بنجاح",
        "error": "حدث خطأ ما",
        "no_data": "لا توجد بيانات"
    },
    "common": {
        "search": "بحث",
        "filter": "تصفية",
        "reset": "إعادة تعيين",
        "yes": "نعم",
        "no": "لا",
        "language": "اللغة",
        "arabic": "العربية",
        "english": "الإنجليزية"
    },
    "system": {
        "app_title": "نظام العيادة",
        "copyright": "جميع الحقوق محفوظة"
    }
}